tella/__init__.py
tella/__version__.py
tella/agents.py
tella/cli.py
tella/curriculum.py
tella/experiment.py
tella/_curriculums/__init__.py
tella/_curriculums/cartpole.py
tella/_curriculums/atari/__init__.py
tella/_curriculums/atari/curriculum.py
tella/_curriculums/atari/environments.py
tella/_curriculums/minigrid/__init__.py
tella/_curriculums/minigrid/m21.py
tella/_curriculums/minigrid/simple.py
tella/_curriculums/minigrid/envs/__init__.py
tella/_curriculums/minigrid/envs/custom_dist_shift.py
tella/_curriculums/minigrid/envs/custom_door_key.py
tella/_curriculums/minigrid/envs/custom_dynamic_obstacles.py
tella/_curriculums/minigrid/envs/custom_fetch.py
tella/_curriculums/minigrid/envs/custom_unlock.py
tella-2.1.0.dist-info/LICENSE
tella-2.1.0.dist-info/METADATA
tella-2.1.0.dist-info/WHEEL
tella-2.1.0.dist-info/top_level.txt
tella-2.1.0.dist-info/RECORD
