Metadata-Version: 2.1
Name: tella
Version: 2.1.0
Summary: library for continual reinforcement learning
License: MIT
Requires-Python: >=3.7
License-File: LICENSE
Requires-Dist: gym[classic_control] (==0.23.1)
Requires-Dist: gym-minigrid (==1.0.3)
Requires-Dist: l2logger (>=1.7.0)
Requires-Dist: matplotlib
Requires-Dist: numpy (>=1.21.4)
Requires-Dist: pyglet (>=1.4.0)
Requires-Dist: pyyaml
Provides-Extra: atari
Requires-Dist: gym[accept-rom-license,atari] ; extra == 'atari'
Provides-Extra: dev
Requires-Dist: pytest ; extra == 'dev'
Requires-Dist: black (==22.1.0) ; extra == 'dev'
